Metadata-Version: 2.1
Name: guessTheNumberSDA
Version: 2.0.0
Summary: Guess the name game. Play to win!
Home-page: UNKNOWN
Author: Guido Xhindoli
Author-email: <mail@gmail.com>
License: UNKNOWN
Keywords: pythonal,pythonal7,game,sda,guess
Platform: UNKNOWN
Classifier: Development Status :: 1 - Planning
Classifier: Intended Audience :: Developers
Classifier: Programming Language :: Python :: 3
Classifier: Operating System :: Unix
Classifier: Operating System :: MacOS :: MacOS X
Classifier: Operating System :: Microsoft :: Windows
